{
	"name": "Tree1",
	"plugin-id": "Sprite",
	"sid": 490933793656424,
	"isGlobal": false,
	"instanceVariables": [],
	"behaviorTypes": [
		{
			"behaviorId": "solid",
			"name": "Solid",
			"sid": 425982321954642
		}
	],
	"effectTypes": [],
	"animations": {
		"items": [
			{
				"frames": [
					{
						"width": 48,
						"height": 64,
						"originX": 0.5,
						"originY": 0.5,
						"originalSource": "",
						"exportFormat": "lossless",
						"exportQuality": 0.8,
						"imageSpriteId": 687710,
						"collisionPoly": {
							"points": [
								0.2708333333333333,
								0.203125,
								0.5,
								0.0625,
								0.6458333333333334,
								0.25,
								0.7167507353283108,
								0.547840118408203,
								0.8418822515578495,
								0.7632258278982981,
								0.5217877342587425,
								0.8368710109165736,
								0.09779357910156243,
								0.7548413957868305,
								0.20833333333333334,
								0.5
							]
						},
						"useCollisionPoly": true,
						"duration": 1
					}
				],
				"sid": 806335967808623,
				"name": "Animation 1",
				"isLooping": false,
				"isPingPong": false,
				"repeatCount": 1,
				"repeatTo": 0,
				"speed": 5
			}
		],
		"subfolders": []
	}
}